mmdeploy_runtime/__init__.py
mmdeploy_runtime/_win_dll_path.py
mmdeploy_runtime/libmmdeploy.so.1
mmdeploy_runtime/libmmdeploy_ort_net.so
mmdeploy_runtime/libonnxruntime.so.1.15.1
mmdeploy_runtime/mmdeploy_runtime.cpython-37m-x86_64-linux-gnu.so
mmdeploy_runtime/version.py
mmdeploy_runtime-1.3.1.dist-info/METADATA
mmdeploy_runtime-1.3.1.dist-info/WHEEL
mmdeploy_runtime-1.3.1.dist-info/top_level.txt
mmdeploy_runtime-1.3.1.dist-info/RECORD
